{
  "generatedAt": "2026-03-29T13:28:34.021Z",
  "academyId": "e2294895-7e39-4f3e-ab46-c4a2fc67870a",
  "version": "1.0.0",
  "period": {
    "preset": "current-month",
    "label": "Este mês",
    "dateFrom": "2026-03-01T03:00:00.000Z",
    "dateTo": "2026-03-29T13:28:34.002Z"
  },
  "statistics": {
    "totalStudents": 1,
    "minorStudents": 0,
    "adultStudents": 1,
    "consentedStudents": 1,
    "expiredConsentCount": 0
  },
  "consents": {
    "versions": [
      {
        "consentType": "Saúde",
        "totalApproved": 1,
        "totalPending": 0
      }
    ],
    "totalConsentApproved": 1,
    "totalConsentPending": 0
  },
  "deletions": {
    "processedRequests": 0,
    "pendingRequests": 0,
    "totalHardDeleted": 0
  },
  "audit": {
    "last90DaysAccess": 5,
    "unauthorizedAttempts": 0,
    "anomalies": []
  },
  "alerts": [],
  "complianceStatus": "COMPLIANT",
  "export": {
    "format": "json",
    "fileName": "LGPD_Compliance_Academia_Conformidade_LGPD_2026-03-01_2026-03-29_1837c2a0-d0eb-42e7-b526-eeed71626384.json",
    "contentType": "application/json",
    "isSigned": false,
    "complianceStatus": "COMPLIANT"
  }
}